{
  "subscribers": "120,000",
  "views": "14,152,693",
  "videos": "193",
  "topVideos": [
    {
      "title": "El Millonario Problema de GANAR en Champions League",
      "views": "885,672",
      "url": "https://www.youtube.com/watch?v=639-Er7x-1c",
      "thumbnail": "https://i.ytimg.com/vi/639-Er7x-1c/mqdefault.jpg"
    },
    {
      "title": "PSG Tiene un NUEVO Problema... Y Está a 40 Metros",
      "views": "747,083",
      "url": "https://www.youtube.com/watch?v=pTzuYWKC-vA",
      "thumbnail": "https://i.ytimg.com/vi/pTzuYWKC-vA/mqdefault.jpg"
    },
    {
      "title": "Cómo el FC 25 ARRUINÓ a la FIFA",
      "views": "710,805",
      "url": "https://www.youtube.com/watch?v=oz3av4iu3HU",
      "thumbnail": "https://i.ytimg.com/vi/oz3av4iu3HU/mqdefault.jpg"
    },
    {
      "title": "China Puso la TRAMPA y el INTER MORDIÓ... ¿Y Ahora?",
      "views": "507,899",
      "url": "https://www.youtube.com/watch?v=GCJ9ndPefeA",
      "thumbnail": "https://i.ytimg.com/vi/GCJ9ndPefeA/mqdefault.jpg"
    },
    {
      "title": "RICOS vs POBRES: Torneos Internacionales de Clubes",
      "views": "455,256",
      "url": "https://www.youtube.com/watch?v=A0wxF_1itMk",
      "thumbnail": "https://i.ytimg.com/vi/A0wxF_1itMk/mqdefault.jpg"
    },
    {
      "title": "Cómo PERDER la Champions y Cobrar MÁS que el Campeón",
      "views": "393,011",
      "url": "https://www.youtube.com/watch?v=52NodEwYc7c",
      "thumbnail": "https://i.ytimg.com/vi/52NodEwYc7c/mqdefault.jpg"
    }
  ],
  "lastUpdated": "2025-05-28T12:20:09.303Z"
}